{
    "success": true,
    "code": 100200,
    "msg": "查询成功",
    "content": [
        {
            "childMenu": [
                {
                    "childMenu": [
                        {
                            "childMenu": null,
                            "id": "31ffce72-7c6a-48ca-a731-cf3b192b839d",
                            "MenuType": "Portal",
                            "MenuLevel": 2,
                            "MenuName": "menu",
                            "MenuFID": "1c9d5585-26e2-46e6-9f4e-b00b47fc9221",
                            "icon": "Tickets",
                            "title": "菜单管理",
                            "component": "permission/menu",
                            "path": "menu",
                            "sonNum": null,
                            "redirect": null,
                            "sortId": 1,
                            "IsDelete": false,
                            "CreateBy": "yixi",
                            "CreateDate": "2024-07-23T20:56:30.477",
                            "UpdateBy": "CamstarAdmin",
                            "UpdateDate": "2024-09-09T19:36:23.037"
                        },
                        {
                            "childMenu": null,
                            "id": "6d686c8d-2767-43ef-851d-122bf3daab70",
                            "MenuType": "Portal",
                            "MenuLevel": 1,
                            "MenuName": "role",
                            "MenuFID": "1c9d5585-26e2-46e6-9f4e-b00b47fc9221",
                            "icon": "Avatar",
                            "title": "角色管理",
                            "component": "permission/role",
                            "path": "role",
                            "sonNum": null,
                            "redirect": null,
                            "sortId": 2,
                            "IsDelete": false,
                            "CreateBy": null,
                            "CreateDate": null,
                            "UpdateBy": "CamstarAdmin",
                            "UpdateDate": "2024-09-09T16:06:54.063"
                        },
                        {
                            "childMenu": null,
                            "id": "60605abf-83af-472f-9b8b-bebfe1f4cd72",
                            "MenuType": "Portal",
                            "MenuLevel": 2,
                            "MenuName": "empolyee",
                            "MenuFID": "1c9d5585-26e2-46e6-9f4e-b00b47fc9221",
                            "icon": "User",
                            "title": "员工管理",
                            "component": "permission/empolyee",
                            "path": "empolyee",
                            "sonNum": null,
                            "redirect": "",
                            "sortId": 4,
                            "IsDelete": false,
                            "CreateBy": "penghui",
                            "CreateDate": "2024-07-23T21:12:56.317",
                            "UpdateBy": "CamstarAdmin",
                            "UpdateDate": "2024-09-09T16:07:00.553"
                        }
                    ],
                    "id": "1c9d5585-26e2-46e6-9f4e-b00b47fc9221",
                    "MenuType": "Portal",
                    "MenuLevel": 1,
                    "MenuName": "Permission",
                    "MenuFID": "43238c7a-8a65-4603-8933-5765f5d31899",
                    "icon": "Monitor",
                    "title": "系统管理",
                    "component": "Layout",
                    "path": "/permission",
                    "sonNum": null,
                    "redirect": null,
                    "sortId": 11,
                    "IsDelete": false,
                    "CreateBy": null,
                    "CreateDate": null,
                    "UpdateBy": null,
                    "UpdateDate": null
                },
                {
                    "childMenu": [
                        {
                            "childMenu": null,
                            "id": "3b13ff9e-0923-41b3-94fa-e513d219facb",
                            "MenuType": "Portal",
                            "MenuLevel": 1,
                            "MenuName": "smtOrderQuary",
                            "MenuFID": "537bb95d-1e81-4adc-a90b-c3b4c1ee8ee2",
                            "icon": "",
                            "title": "SMT工单查询",
                            "component": "workOrderManage/smtOrderQuary",
                            "path": "smtOrderQuary",
                            "sonNum": null,
                            "redirect": "",
                            "sortId": 1,
                            "IsDelete": false,
                            "CreateBy": "CamstarAdmin",
                            "CreateDate": "2024-09-03T15:37:46.443",
                            "UpdateBy": "CamstarAdmin",
                            "UpdateDate": "2024-09-05T21:31:36.83"
                        },
                        {
                            "childMenu": null,
                            "id": "71433a44-1f78-4740-9732-d3831ed4f5c9",
                            "MenuType": "Portal",
                            "MenuLevel": 1,
                            "MenuName": "SmtOrderQuary1",
                            "MenuFID": "537bb95d-1e81-4adc-a90b-c3b4c1ee8ee2",
                            "icon": "",
                            "title": "ECN单据查询",
                            "component": "workOrderManage/smtOrderQuary2",
                            "path": "smtOrderQuary2",
                            "sonNum": null,
                            "redirect": "",
                            "sortId": 2,
                            "IsDelete": false,
                            "CreateBy": "CamstarAdmin",
                            "CreateDate": "2024-09-04T13:39:17.843",
                            "UpdateBy": "CamstarAdmin",
                            "UpdateDate": "2024-09-05T15:07:11.547"
                        },
                        {
                            "childMenu": null,
                            "id": "45624f67-5fbf-47ad-a079-83022a6f2398",
                            "MenuType": "Portal",
                            "MenuLevel": 1,
                            "MenuName": "SmtOrderQuary3",
                            "MenuFID": "537bb95d-1e81-4adc-a90b-c3b4c1ee8ee2",
                            "icon": "",
                            "title": "内联单维护",
                            "component": "workOrderManage/smtOrderQuary3",
                            "path": "smtOrderQuary3",
                            "sonNum": null,
                            "redirect": "",
                            "sortId": 3,
                            "IsDelete": false,
                            "CreateBy": "CamstarAdmin",
                            "CreateDate": "2024-09-04T13:38:35.973",
                            "UpdateBy": "CamstarAdmin",
                            "UpdateDate": "2024-09-05T15:07:15.207"
                        }
                    ],
                    "id": "537bb95d-1e81-4adc-a90b-c3b4c1ee8ee2",
                    "MenuType": "Portal",
                    "MenuLevel": 1,
                    "MenuName": "workOrderManage",
                    "MenuFID": "43238c7a-8a65-4603-8933-5765f5d31899",
                    "icon": "Files",
                    "title": "工单管理",
                    "component": "Layout",
                    "path": "/workOrderManage",
                    "sonNum": null,
                    "redirect": null,
                    "sortId": 12,
                    "IsDelete": false,
                    "CreateBy": null,
                    "CreateDate": "2024-08-20T15:07:54.953",
                    "UpdateBy": "CamstarAdmin",
                    "UpdateDate": "2024-09-10T09:13:23.74"
                },
                {
                    "childMenu": [
                        {
                            "childMenu": null,
                            "id": "875d1091-149d-4ce2-bca4-4ff94154bd8e",
                            "MenuType": "Portal",
                            "MenuLevel": 1,
                            "MenuName": "materialBasic",
                            "MenuFID": "a0e0bb70-b7c2-44dc-b54d-f6c3d7e475c2",
                            "icon": "Tickets",
                            "title": "物料基础数据",
                            "component": "materialManage/materialBasic",
                            "path": "materialBasic",
                            "sonNum": null,
                            "redirect": "",
                            "sortId": 1,
                            "IsDelete": false,
                            "CreateBy": "CamstarAdmin",
                            "CreateDate": "2024-08-29T09:24:05.047",
                            "UpdateBy": "CamstarAdmin",
                            "UpdateDate": "2024-09-05T21:31:26.35"
                        },
                        {
                            "childMenu": null,
                            "id": "88c8b8f4-5c9e-4802-af1b-a0d175affee0",
                            "MenuType": "Portal",
                            "MenuLevel": 1,
                            "MenuName": "materialReques",
                            "MenuFID": "a0e0bb70-b7c2-44dc-b54d-f6c3d7e475c2",
                            "icon": "Box",
                            "title": "物料申请",
                            "component": "materialManage/materialReques",
                            "path": "materialReques",
                            "sonNum": null,
                            "redirect": "",
                            "sortId": 21,
                            "IsDelete": false,
                            "CreateBy": "CamstarAdmin",
                            "CreateDate": "2024-08-20T15:09:07.15",
                            "UpdateBy": "CamstarAdmin",
                            "UpdateDate": "2024-09-09T09:48:22.997"
                        }
                    ],
                    "id": "a0e0bb70-b7c2-44dc-b54d-f6c3d7e475c2",
                    "MenuType": "Portal",
                    "MenuLevel": 1,
                    "MenuName": "materialManage",
                    "MenuFID": "43238c7a-8a65-4603-8933-5765f5d31899",
                    "icon": "Box",
                    "title": "物料管理",
                    "component": "Layout",
                    "path": "/materialManage",
                    "sonNum": null,
                    "redirect": null,
                    "sortId": 13,
                    "IsDelete": false,
                    "CreateBy": null,
                    "CreateDate": "2024-08-29T09:21:32.34",
                    "UpdateBy": "CamstarAdmin",
                    "UpdateDate": "2024-09-10T09:13:35.08"
                },
                {
                    "childMenu": [
                        {
                            "childMenu": [
                                {
                                    "childMenu": null,
                                    "id": "c83adfa3-e9a1-49bc-b41c-80259f52e4c8",
                                    "MenuType": "Portal",
                                    "MenuLevel": 2,
                                    "MenuName": "firstInspection",
                                    "MenuFID": "1bfedf0e-4c05-4634-9b6f-1e6a45940056",
                                    "icon": "",
                                    "title": "首检",
                                    "component": "smtSpotCheck/basic/firstInspection",
                                    "path": "firstInspection",
                                    "sonNum": null,
                                    "redirect": null,
                                    "sortId": 1,
                                    "IsDelete": false,
                                    "CreateBy": null,
                                    "CreateDate": null,
                                    "UpdateBy": "CamstarAdmin",
                                    "UpdateDate": "2024-09-09T16:07:14.783"
                                },
                                {
                                    "childMenu": null,
                                    "id": "91be957f-9d63-46f0-b125-bcf9fa5a9b4d",
                                    "MenuType": "Portal",
                                    "MenuLevel": 2,
                                    "MenuName": "patrol",
                                    "MenuFID": "1bfedf0e-4c05-4634-9b6f-1e6a45940056",
                                    "icon": "",
                                    "title": "巡检",
                                    "component": "smtSpotCheck/basic/patrol",
                                    "path": "patrol",
                                    "sonNum": null,
                                    "redirect": null,
                                    "sortId": 2,
                                    "IsDelete": false,
                                    "CreateBy": null,
                                    "CreateDate": null,
                                    "UpdateBy": "CamstarAdmin",
                                    "UpdateDate": "2024-09-09T16:07:22.63"
                                },
                                {
                                    "childMenu": null,
                                    "id": "abed0c0b-436b-4c3a-a2e6-c936630587d9",
                                    "MenuType": "Portal",
                                    "MenuLevel": 2,
                                    "MenuName": "eqInspection",
                                    "MenuFID": "1bfedf0e-4c05-4634-9b6f-1e6a45940056",
                                    "icon": "",
                                    "title": "设备点检",
                                    "component": "smtSpotCheck/basic/eqInspection",
                                    "path": "eqInspection",
                                    "sonNum": null,
                                    "redirect": null,
                                    "sortId": 3,
                                    "IsDelete": false,
                                    "CreateBy": null,
                                    "CreateDate": null,
                                    "UpdateBy": "CamstarAdmin",
                                    "UpdateDate": "2024-09-09T16:07:28.84"
                                },
                                {
                                    "childMenu": null,
                                    "id": "3c31346b-f6c8-4aae-bd56-55424f70d220",
                                    "MenuType": "Portal",
                                    "MenuLevel": 2,
                                    "MenuName": "proInspection",
                                    "MenuFID": "1bfedf0e-4c05-4634-9b6f-1e6a45940056",
                                    "icon": "",
                                    "title": "4M点检",
                                    "component": "smtSpotCheck/basic/proInspection",
                                    "path": "proInspection",
                                    "sonNum": null,
                                    "redirect": null,
                                    "sortId": 4,
                                    "IsDelete": false,
                                    "CreateBy": null,
                                    "CreateDate": null,
                                    "UpdateBy": "CamstarAdmin",
                                    "UpdateDate": "2024-09-09T16:07:35.373"
                                },
                                {
                                    "childMenu": null,
                                    "id": "8e51606b-b153-4e65-980e-8651cda21379",
                                    "MenuType": "Portal",
                                    "MenuLevel": 2,
                                    "MenuName": "classInspection",
                                    "MenuFID": "1bfedf0e-4c05-4634-9b6f-1e6a45940056",
                                    "icon": "",
                                    "title": "开班点检",
                                    "component": "smtSpotCheck/basic/classInspection",
                                    "path": "classInspection",
                                    "sonNum": null,
                                    "redirect": "",
                                    "sortId": 15,
                                    "IsDelete": false,
                                    "CreateBy": "yixi",
                                    "CreateDate": "2024-07-24T10:35:51.09",
                                    "UpdateBy": "CamstarAdmin",
                                    "UpdateDate": "2024-09-09T16:07:48.01"
                                }
                            ],
                            "id": "1bfedf0e-4c05-4634-9b6f-1e6a45940056",
                            "MenuType": "Portal",
                            "MenuLevel": 1,
                            "MenuName": "Basic",
                            "MenuFID": "bcdb980f-6b84-4ddc-a4a3-b2afafa1862b",
                            "icon": "List",
                            "title": "IPQC",
                            "component": "",
                            "path": "basic",
                            "sonNum": null,
                            "redirect": null,
                            "sortId": 121,
                            "IsDelete": false,
                            "CreateBy": null,
                            "CreateDate": null,
                            "UpdateBy": "CamstarAdmin",
                            "UpdateDate": "2024-08-02T19:05:11.017"
                        },
                        {
                            "childMenu": [
                                {
                                    "childMenu": null,
                                    "id": "a24e29a5-1ccb-4dad-ad98-124252b675c9",
                                    "MenuType": "Portal",
                                    "MenuLevel": 1,
                                    "MenuName": "ipqcResult",
                                    "MenuFID": "dcd77d30-015a-4188-bd8d-08f42fc2e2eb",
                                    "icon": "",
                                    "title": "点检结果",
                                    "component": "smtSpotCheck/outcome/ipqcResult",
                                    "path": "ipqcResult",
                                    "sonNum": null,
                                    "redirect": null,
                                    "sortId": 1,
                                    "IsDelete": false,
                                    "CreateBy": null,
                                    "CreateDate": null,
                                    "UpdateBy": "CamstarAdmin",
                                    "UpdateDate": "2024-09-09T19:51:43.277"
                                },
                                {
                                    "childMenu": null,
                                    "id": "250124d0-c8c0-42de-a40c-9f0ca65c8a6f",
                                    "MenuType": "Portal",
                                    "MenuLevel": 1,
                                    "MenuName": "FirstArticle",
                                    "MenuFID": "dcd77d30-015a-4188-bd8d-08f42fc2e2eb",
                                    "icon": "",
                                    "title": "首件结果",
                                    "component": "smtSpotCheck/outcome/firstArticle",
                                    "path": "firstArticle",
                                    "sonNum": null,
                                    "redirect": null,
                                    "sortId": 3,
                                    "IsDelete": false,
                                    "CreateBy": null,
                                    "CreateDate": null,
                                    "UpdateBy": "CamstarAdmin",
                                    "UpdateDate": "2024-09-09T19:51:55.18"
                                }
                            ],
                            "id": "dcd77d30-015a-4188-bd8d-08f42fc2e2eb",
                            "MenuType": "Portal",
                            "MenuLevel": 1,
                            "MenuName": "outcome",
                            "MenuFID": "bcdb980f-6b84-4ddc-a4a3-b2afafa1862b",
                            "icon": "Tickets",
                            "title": "检验结果",
                            "component": "",
                            "path": "outcome",
                            "sonNum": null,
                            "redirect": null,
                            "sortId": 122,
                            "IsDelete": false,
                            "CreateBy": null,
                            "CreateDate": null,
                            "UpdateBy": "CamstarAdmin",
                            "UpdateDate": "2024-09-09T19:55:02.09"
                        },
                        {
                            "childMenu": [
                                {
                                    "childMenu": null,
                                    "id": "575d2488-5577-44df-9d50-82175f4c5d13",
                                    "MenuType": "Portal",
                                    "MenuLevel": 1,
                                    "MenuName": "repair",
                                    "MenuFID": "d741488e-4463-4828-ba53-891ab004d998",
                                    "icon": "",
                                    "title": "返修",
                                    "component": "maintenance/repair",
                                    "path": "repair",
                                    "sonNum": null,
                                    "redirect": "",
                                    "sortId": 1,
                                    "IsDelete": false,
                                    "CreateBy": "CamstarAdmin",
                                    "CreateDate": "2024-08-16T17:32:14.677",
                                    "UpdateBy": "CamstarAdmin",
                                    "UpdateDate": "2024-09-09T16:08:12.703"
                                }
                            ],
                            "id": "d741488e-4463-4828-ba53-891ab004d998",
                            "MenuType": "Portal",
                            "MenuLevel": 1,
                            "MenuName": "Repair",
                            "MenuFID": "bcdb980f-6b84-4ddc-a4a3-b2afafa1862b",
                            "icon": "Cpu",
                            "title": "SMT在线返修",
                            "component": "",
                            "path": "maintenance",
                            "sonNum": null,
                            "redirect": null,
                            "sortId": 123,
                            "IsDelete": false,
                            "CreateBy": null,
                            "CreateDate": "2024-08-21T17:19:52.697",
                            "UpdateBy": "CamstarAdmin",
                            "UpdateDate": "2024-09-09T19:54:52.163"
                        }
                    ],
                    "id": "bcdb980f-6b84-4ddc-a4a3-b2afafa1862b",
                    "MenuType": "Portal",
                    "MenuLevel": 1,
                    "MenuName": "smtSpotCheck",
                    "MenuFID": "43238c7a-8a65-4603-8933-5765f5d31899",
                    "icon": "Edit",
                    "title": "质量管理",
                    "component": "Layout",
                    "path": "/smtSpotCheck",
                    "sonNum": null,
                    "redirect": null,
                    "sortId": 14,
                    "IsDelete": false,
                    "CreateBy": null,
                    "CreateDate": null,
                    "UpdateBy": "CamstarAdmin",
                    "UpdateDate": "2024-09-10T09:13:47.513"
                },
                {
                    "childMenu": [
                        {
                            "childMenu": null,
                            "id": "6fea512d-b99e-4110-b96b-cac788d1467e",
                            "MenuType": "Portal",
                            "MenuLevel": 1,
                            "MenuName": "deviceLedger",
                            "MenuFID": "71f98c7a-8a65-4603-8933-5765f5d31899",
                            "icon": "Tickets",
                            "title": "设备台账",
                            "component": "deviceManage/deviceLedger",
                            "path": "deviceLedger",
                            "sonNum": null,
                            "redirect": "",
                            "sortId": 1,
                            "IsDelete": false,
                            "CreateBy": "CamstarAdmin",
                            "CreateDate": "2024-07-30T11:05:33.973",
                            "UpdateBy": "CamstarAdmin",
                            "UpdateDate": "2024-09-10T15:37:39.13"
                        },
                        {
                            "childMenu": [
                                {
                                    "childMenu": null,
                                    "id": "e182dfcd-5a44-4d87-9ef6-5b6e78f9d22c",
                                    "MenuType": "Portal",
                                    "MenuLevel": 1,
                                    "MenuName": "faultCodes",
                                    "MenuFID": "6a63e11f-c1ff-40ee-93cb-801508c3556b",
                                    "icon": "",
                                    "title": "设备故障代码维护",
                                    "component": "eqMaintain/faultCodes",
                                    "path": "faultCodes",
                                    "sonNum": null,
                                    "redirect": "",
                                    "sortId": 1,
                                    "IsDelete": false,
                                    "CreateBy": "CamstarAdmin",
                                    "CreateDate": "2024-09-04T13:44:38.203",
                                    "UpdateBy": "CamstarAdmin",
                                    "UpdateDate": "2024-09-10T15:39:33.853"
                                },
                                {
                                    "childMenu": null,
                                    "id": "08786100-9521-40b8-9861-b4e5b4e398b5",
                                    "MenuType": "Portal",
                                    "MenuLevel": 1,
                                    "MenuName": "inspectRecords",
                                    "MenuFID": "6a63e11f-c1ff-40ee-93cb-801508c3556b",
                                    "icon": "",
                                    "title": "设备点检记录查询",
                                    "component": "fixtureManagement/inspectRecords",
                                    "path": "inspectRecords",
                                    "sonNum": null,
                                    "redirect": "",
                                    "sortId": 2,
                                    "IsDelete": false,
                                    "CreateBy": "CamstarAdmin",
                                    "CreateDate": "2024-09-04T13:43:53.277",
                                    "UpdateBy": "CamstarAdmin",
                                    "UpdateDate": "2024-09-10T15:45:10.417"
                                },
                                {
                                    "childMenu": null,
                                    "id": "42eb601a-a9ec-4ffc-98f7-ac8b1de577d2",
                                    "MenuType": "Portal",
                                    "MenuLevel": 1,
                                    "MenuName": "upkeep",
                                    "MenuFID": "6a63e11f-c1ff-40ee-93cb-801508c3556b",
                                    "icon": "",
                                    "title": "设备保养记录查询",
                                    "component": "fixtureManagement/upkeep",
                                    "path": "upkeep",
                                    "sonNum": null,
                                    "redirect": "",
                                    "sortId": 3,
                                    "IsDelete": false,
                                    "CreateBy": "CamstarAdmin",
                                    "CreateDate": "2024-09-04T13:44:05.69",
                                    "UpdateBy": "CamstarAdmin",
                                    "UpdateDate": "2024-09-10T15:45:38.43"
                                },
                                {
                                    "childMenu": null,
                                    "id": "30118303-e45a-40bc-bbfa-5ce41fc78b36",
                                    "MenuType": "Portal",
                                    "MenuLevel": 1,
                                    "MenuName": "repair",
                                    "MenuFID": "6a63e11f-c1ff-40ee-93cb-801508c3556b",
                                    "icon": "",
                                    "title": "设备维修记录查询",
                                    "component": "fixtureManagement/repair",
                                    "path": "repair",
                                    "sonNum": null,
                                    "redirect": "",
                                    "sortId": 4,
                                    "IsDelete": false,
                                    "CreateBy": "CamstarAdmin",
                                    "CreateDate": "2024-09-04T13:44:56.27",
                                    "UpdateBy": "CamstarAdmin",
                                    "UpdateDate": "2024-09-10T15:46:01.937"
                                }
                            ],
                            "id": "6a63e11f-c1ff-40ee-93cb-801508c3556b",
                            "MenuType": "Portal",
                            "MenuLevel": 1,
                            "MenuName": "eqMaintain",
                            "MenuFID": "71f98c7a-8a65-4603-8933-5765f5d31899",
                            "icon": "Box",
                            "title": "设备维护",
                            "component": "",
                            "path": "eqMaintain",
                            "sonNum": null,
                            "redirect": null,
                            "sortId": 3,
                            "IsDelete": false,
                            "CreateBy": null,
                            "CreateDate": "2024-09-04T13:42:57.267",
                            "UpdateBy": "CamstarAdmin",
                            "UpdateDate": "2024-09-10T15:38:34.06"
                        },
                        {
                            "childMenu": [
                                {
                                    "childMenu": null,
                                    "id": "b191cef3-968a-4468-92f3-46ba5596702f",
                                    "MenuType": "Portal",
                                    "MenuLevel": 1,
                                    "MenuName": "fixtureType",
                                    "MenuFID": "6786b6bf-514f-4047-9126-d127370cff4e",
                                    "icon": "",
                                    "title": "工治具型号维护",
                                    "component": "fixtureManagement/fixtureType",
                                    "path": "fixtureType",
                                    "sonNum": null,
                                    "redirect": "",
                                    "sortId": 1,
                                    "IsDelete": false,
                                    "CreateBy": "CamstarAdmin",
                                    "CreateDate": "2024-09-10T15:41:25.253",
                                    "UpdateBy": "CamstarAdmin",
                                    "UpdateDate": "2024-09-10T15:44:02.703"
                                },
                                {
                                    "childMenu": null,
                                    "id": "d3478ac6-2e79-457f-97f5-c6fd3a0a9070",
                                    "MenuType": "Portal",
                                    "MenuLevel": 1,
                                    "MenuName": "fixtureEntry",
                                    "MenuFID": "6786b6bf-514f-4047-9126-d127370cff4e",
                                    "icon": "",
                                    "title": "工治具录入",
                                    "component": "fixtureManagement/fixtureEntry",
                                    "path": "fixtureEntry",
                                    "sonNum": null,
                                    "redirect": "",
                                    "sortId": 2,
                                    "IsDelete": false,
                                    "CreateBy": "CamstarAdmin",
                                    "CreateDate": "2024-08-26T11:36:48.717",
                                    "UpdateBy": "CamstarAdmin",
                                    "UpdateDate": "2024-09-10T16:51:26.173"
                                },
                                {
                                    "childMenu": null,
                                    "id": "c66c360c-80b5-4c62-8cbe-0a3534cd820b",
                                    "MenuType": "Portal",
                                    "MenuLevel": 1,
                                    "MenuName": "FixtureProduct",
                                    "MenuFID": "6786b6bf-514f-4047-9126-d127370cff4e",
                                    "icon": "",
                                    "title": "产品消耗",
                                    "component": "fixtureManagement/fixtureProduct",
                                    "path": "fixtureProduct",
                                    "sonNum": null,
                                    "redirect": "",
                                    "sortId": 3,
                                    "IsDelete": false,
                                    "CreateBy": "CamstarAdmin",
                                    "CreateDate": "2024-08-26T11:37:01.233",
                                    "UpdateBy": "CamstarAdmin",
                                    "UpdateDate": "2024-09-03T17:04:41.567"
                                },
                                {
                                    "childMenu": null,
                                    "id": "0d77eb48-d4be-40d0-8792-4b4181a85de6",
                                    "MenuType": "Portal",
                                    "MenuLevel": 1,
                                    "MenuName": "fixtureIssue",
                                    "MenuFID": "6786b6bf-514f-4047-9126-d127370cff4e",
                                    "icon": "",
                                    "title": "工单查询",
                                    "component": "fixtureManagement/fixtureIssue",
                                    "path": "fixtureIssue",
                                    "sonNum": null,
                                    "redirect": "",
                                    "sortId": 4,
                                    "IsDelete": false,
                                    "CreateBy": "CamstarAdmin",
                                    "CreateDate": "2024-08-26T11:37:17.203",
                                    "UpdateBy": "CamstarAdmin",
                                    "UpdateDate": "2024-09-09T15:35:50.887"
                                }
                            ],
                            "id": "6786b6bf-514f-4047-9126-d127370cff4e",
                            "MenuType": "Portal",
                            "MenuLevel": 1,
                            "MenuName": "FixtureManagement",
                            "MenuFID": "71f98c7a-8a65-4603-8933-5765f5d31899",
                            "icon": "Cpu",
                            "title": "工治具管理",
                            "component": "",
                            "path": "fixtureManagement",
                            "sonNum": null,
                            "redirect": null,
                            "sortId": 132,
                            "IsDelete": false,
                            "CreateBy": null,
                            "CreateDate": "2024-08-26T11:34:56.83",
                            "UpdateBy": "CamstarAdmin",
                            "UpdateDate": "2024-09-10T13:56:32.11"
                        }
                    ],
                    "id": "71f98c7a-8a65-4603-8933-5765f5d31899",
                    "MenuType": "Portal",
                    "MenuLevel": 1,
                    "MenuName": "DeviceManage",
                    "MenuFID": "43238c7a-8a65-4603-8933-5765f5d31899",
                    "icon": "SetUp",
                    "title": "设备管理",
                    "component": "Layout",
                    "path": "/deviceManage",
                    "sonNum": null,
                    "redirect": null,
                    "sortId": 15,
                    "IsDelete": false,
                    "CreateBy": null,
                    "CreateDate": null,
                    "UpdateBy": "CamstarAdmin",
                    "UpdateDate": "2024-09-10T09:13:56"
                },
                {
                    "childMenu": [
                        {
                            "childMenu": null,
                            "id": "5645b88e-a152-4ae3-8fbb-c793e8bbf02c",
                            "MenuType": "Portal",
                            "MenuLevel": 1,
                            "MenuName": "MaterialBasic2",
                            "MenuFID": "0f0a91ff-4002-444b-b2b2-90a98e9028c4",
                            "icon": "Tickets",
                            "title": "SMT物料备料看板",
                            "component": "materialManage/materialBasic2",
                            "path": "materialBasic2",
                            "sonNum": 0,
                            "redirect": "",
                            "sortId": 1,
                            "IsDelete": false,
                            "CreateBy": "CamstarAdmin",
                            "CreateDate": "2024-09-05T15:16:38.707",
                            "UpdateBy": "CamstarAdmin",
                            "UpdateDate": "2024-09-05T15:16:19.2"
                        }
                    ],
                    "id": "0f0a91ff-4002-444b-b2b2-90a98e9028c4",
                    "MenuType": "Portal",
                    "MenuLevel": 1,
                    "MenuName": "materialManage2",
                    "MenuFID": "43238c7a-8a65-4603-8933-5765f5d31899",
                    "icon": "Tickets",
                    "title": "报表与看板",
                    "component": "Layout",
                    "path": "/materialManage2",
                    "sonNum": null,
                    "redirect": null,
                    "sortId": 17,
                    "IsDelete": false,
                    "CreateBy": null,
                    "CreateDate": "2024-09-05T15:06:31.42",
                    "UpdateBy": "CamstarAdmin",
                    "UpdateDate": "2024-09-05T15:15:13.13"
                }
            ],
            "id": "43238c7a-8a65-4603-8933-5765f5d31899",
            "MenuType": "Portal",
            "MenuLevel": 0,
            "MenuName": "Portal",
            "MenuFID": "",
            "icon": "",
            "title": "Portal",
            "component": "",
            "path": "",
            "sonNum": 4,
            "redirect": null,
            "sortId": 1,
            "IsDelete": false,
            "CreateBy": null,
            "CreateDate": null,
            "UpdateBy": null,
            "UpdateDate": null
        },
        {
            "childMenu": [
                {
                    "childMenu": [
                        {
                            "childMenu": null,
                            "id": "e508c0dd-3514-4bc3-b3b8-2408bce71798",
                            "MenuType": "PDA",
                            "MenuLevel": 2,
                            "MenuName": "../static/svg/rysg.svg",
                            "MenuFID": "ef661f41-4383-4050-b8f6-32778eb26c8e",
                            "icon": "",
                            "title": "人员上岗",
                            "component": "",
                            "path": "personnelDuty",
                            "sonNum": null,
                            "redirect": "/pages/permanage/personnelDuty",
                            "sortId": 1,
                            "IsDelete": false,
                            "CreateBy": "yixi",
                            "CreateDate": "2024-07-25T10:52:09.507",
                            "UpdateBy": "CamstarAdmin",
                            "UpdateDate": "2024-08-02T19:09:16.443"
                        },
                        {
                            "childMenu": null,
                            "id": "9c02365b-7566-403c-9156-2c2f2dfcba2d",
                            "MenuType": "PDA",
                            "MenuLevel": 1,
                            "MenuName": "../static/svg/tb.svg",
                            "MenuFID": "ef661f41-4383-4050-b8f6-32778eb26c8e",
                            "icon": "",
                            "title": "贴合脱泡",
                            "component": "",
                            "path": "jointdeaeration",
                            "sonNum": null,
                            "redirect": "/pages/permanage/jointdeaeration/choice",
                            "sortId": 2,
                            "IsDelete": false,
                            "CreateBy": "yixi",
                            "CreateDate": "2024-08-15T16:44:13.687",
                            "UpdateBy": "CamstarAdmin",
                            "UpdateDate": "2024-08-16T11:41:05.55"
                        },
                        {
                            "childMenu": null,
                            "id": "aafda187-4785-4284-bce9-495d19170e8f",
                            "MenuType": "PDA",
                            "MenuLevel": 2,
                            "MenuName": "../static/svg/turnBox2.svg",
                            "MenuFID": "ef661f41-4383-4050-b8f6-32778eb26c8e",
                            "icon": "",
                            "title": "SMT半成品拆箱",
                            "component": "",
                            "path": "turnBox",
                            "sonNum": null,
                            "redirect": "/pages/permanage/turnBox",
                            "sortId": 3,
                            "IsDelete": false,
                            "CreateBy": "yixi",
                            "CreateDate": "2024-08-16T11:39:38.287",
                            "UpdateBy": "CamstarAdmin",
                            "UpdateDate": "2024-08-19T15:14:05.94"
                        },
                        {
                            "childMenu": null,
                            "id": "f7aa91c9-30f3-4d30-8a0a-f7a862b3e7bd",
                            "MenuType": "PDA",
                            "MenuLevel": 2,
                            "MenuName": "../static/svg/turnBox.svg",
                            "MenuFID": "ef661f41-4383-4050-b8f6-32778eb26c8e",
                            "icon": "",
                            "title": "周转箱操作",
                            "component": "",
                            "path": "turnoverBox",
                            "sonNum": null,
                            "redirect": "/pages/permanage/turnoverBox/index",
                            "sortId": 3,
                            "IsDelete": false,
                            "CreateBy": "yixi",
                            "CreateDate": "2024-08-23T11:09:50.653",
                            "UpdateBy": "CamstarAdmin",
                            "UpdateDate": "2024-08-23T11:26:34.217"
                        },
                        {
                            "childMenu": null,
                            "id": "ff0bbde1-8b37-4e8f-81e1-f4d2c7c2e183",
                            "MenuType": "PDA",
                            "MenuLevel": 2,
                            "MenuName": "../static/svg/cprk.svg",
                            "MenuFID": "ef661f41-4383-4050-b8f6-32778eb26c8e",
                            "icon": "",
                            "title": "SMT半成品入库",
                            "component": "",
                            "path": "semiFinish",
                            "sonNum": null,
                            "redirect": "/pages/permanage/semiFinish/index",
                            "sortId": 4,
                            "IsDelete": false,
                            "CreateBy": "yixi",
                            "CreateDate": "2024-08-16T17:21:12.39",
                            "UpdateBy": "CamstarAdmin",
                            "UpdateDate": "2024-08-26T17:31:56.403"
                        },
                        {
                            "childMenu": null,
                            "id": "a58be8c5-81d0-4cf8-a116-a76fd8728976",
                            "MenuType": "PDA",
                            "MenuLevel": 2,
                            "MenuName": "../static/svg/packing.svg",
                            "MenuFID": "ef661f41-4383-4050-b8f6-32778eb26c8e",
                            "icon": "",
                            "title": "屏半成品装箱",
                            "component": "",
                            "path": "screenPacka",
                            "sonNum": null,
                            "redirect": "/pages/permanage/screenPacka",
                            "sortId": 5,
                            "IsDelete": false,
                            "CreateBy": "yixi",
                            "CreateDate": "2024-08-19T15:33:08.323",
                            "UpdateBy": "CamstarAdmin",
                            "UpdateDate": "2024-08-19T16:09:34.983"
                        },
                        {
                            "childMenu": null,
                            "id": "35be1c58-5329-4fcc-800e-7c118bc5b9e4",
                            "MenuType": "PDA",
                            "MenuLevel": 2,
                            "MenuName": "../static/svg/turnBox3.svg",
                            "MenuFID": "ef661f41-4383-4050-b8f6-32778eb26c8e",
                            "icon": "",
                            "title": "屏半成品拆箱",
                            "component": "",
                            "path": "screenUnbox",
                            "sonNum": null,
                            "redirect": "/pages/permanage/screenUnbox",
                            "sortId": 6,
                            "IsDelete": false,
                            "CreateBy": "yixi",
                            "CreateDate": "2024-08-19T16:00:19.02",
                            "UpdateBy": "CamstarAdmin",
                            "UpdateDate": "2024-08-19T16:09:41.92"
                        }
                    ],
                    "id": "ef661f41-4383-4050-b8f6-32778eb26c8e",
                    "MenuType": "PDA",
                    "MenuLevel": 1,
                    "MenuName": "生产管理",
                    "MenuFID": "32138c7a-8a65-4603-8933-5765f5d31543",
                    "icon": "",
                    "title": "生产管理",
                    "component": "",
                    "path": "生产管理",
                    "sonNum": null,
                    "redirect": "",
                    "sortId": 1,
                    "IsDelete": false,
                    "CreateBy": "yixi",
                    "CreateDate": "2024-07-25T10:51:11.53",
                    "UpdateBy": "CamstarAdmin",
                    "UpdateDate": "2024-08-26T20:38:25.207"
                },
                {
                    "childMenu": [
                        {
                            "childMenu": null,
                            "id": "4461d864-3921-4884-9013-9e38ce272c62",
                            "MenuType": "PDA",
                            "MenuLevel": 2,
                            "MenuName": "../static/svg/first.svg",
                            "MenuFID": "1cb51610-ab18-45cb-8baf-05ddce79a135",
                            "icon": "",
                            "title": "首检",
                            "component": "FI",
                            "path": "firstInspection",
                            "sonNum": null,
                            "redirect": "/pages/mes/firstInspection/index?type=FI",
                            "sortId": 1,
                            "IsDelete": false,
                            "CreateBy": "10011",
                            "CreateDate": "2024-07-09T19:14:55.82",
                            "UpdateBy": "CamstarAdmin",
                            "UpdateDate": "2024-08-02T19:07:53.753"
                        },
                        {
                            "childMenu": null,
                            "id": "0c6fb40e-ab01-47fe-89db-bb4be20b0a3d",
                            "MenuType": "PDA",
                            "MenuLevel": 2,
                            "MenuName": "../static/svg/inset.svg",
                            "MenuFID": "1cb51610-ab18-45cb-8baf-05ddce79a135",
                            "icon": "",
                            "title": "巡检",
                            "component": "RI",
                            "path": "patrol",
                            "sonNum": null,
                            "redirect": "/pages/mes/firstInspection/index?type=RI",
                            "sortId": 2,
                            "IsDelete": false,
                            "CreateBy": "10011",
                            "CreateDate": "2024-07-09T19:19:06.617",
                            "UpdateBy": "CamstarAdmin",
                            "UpdateDate": "2024-08-02T19:07:59.18"
                        },
                        {
                            "childMenu": null,
                            "id": "64067526-7ee6-4ce9-9223-de222fa6e021",
                            "MenuType": "PDA",
                            "MenuLevel": 2,
                            "MenuName": "../static/svg/eq.svg",
                            "MenuFID": "1cb51610-ab18-45cb-8baf-05ddce79a135",
                            "icon": "",
                            "title": "设备点检",
                            "component": "EI",
                            "path": "eqInspection",
                            "sonNum": null,
                            "redirect": "/pages/mes/firstInspection/index?type=EI",
                            "sortId": 3,
                            "IsDelete": false,
                            "CreateBy": "yixi",
                            "CreateDate": "2024-07-24T16:19:38.59",
                            "UpdateBy": "CamstarAdmin",
                            "UpdateDate": "2024-08-02T19:08:58.32"
                        },
                        {
                            "childMenu": null,
                            "id": "2335a6f8-7260-43cc-b1e3-eabf690e8cd1",
                            "MenuType": "PDA",
                            "MenuLevel": 2,
                            "MenuName": "../static/svg/wo.svg",
                            "MenuFID": "1cb51610-ab18-45cb-8baf-05ddce79a135",
                            "icon": "",
                            "title": "4M点检",
                            "component": "4I",
                            "path": "proInspection",
                            "sonNum": null,
                            "redirect": "/pages/mes/firstInspection/index?type=4I",
                            "sortId": 4,
                            "IsDelete": false,
                            "CreateBy": "yixi",
                            "CreateDate": "2024-07-24T16:22:48.563",
                            "UpdateBy": "CamstarAdmin",
                            "UpdateDate": "2024-08-02T19:08:29.587"
                        },
                        {
                            "childMenu": null,
                            "id": "65fa6270-fa7f-4ae7-80d0-665d9d9e3761",
                            "MenuType": "PDA",
                            "MenuLevel": 2,
                            "MenuName": "../static/svg/class.svg",
                            "MenuFID": "1cb51610-ab18-45cb-8baf-05ddce79a135",
                            "icon": "",
                            "title": "开班点检",
                            "component": "CI",
                            "path": "classInspection",
                            "sonNum": null,
                            "redirect": "/pages/mes/firstInspection/index?type=CI",
                            "sortId": 5,
                            "IsDelete": false,
                            "CreateBy": "yixi",
                            "CreateDate": "2024-07-24T16:24:46.697",
                            "UpdateBy": "CamstarAdmin",
                            "UpdateDate": "2024-08-02T19:08:44.707"
                        }
                    ],
                    "id": "1cb51610-ab18-45cb-8baf-05ddce79a135",
                    "MenuType": "PDA",
                    "MenuLevel": 1,
                    "MenuName": "IPQC",
                    "MenuFID": "32138c7a-8a65-4603-8933-5765f5d31543",
                    "icon": "",
                    "title": "质量管理",
                    "component": "",
                    "path": "IPQC",
                    "sonNum": null,
                    "redirect": null,
                    "sortId": 2,
                    "IsDelete": false,
                    "CreateBy": "10011",
                    "CreateDate": "2024-07-09T19:11:10.647",
                    "UpdateBy": "CamstarAdmin",
                    "UpdateDate": "2024-08-26T20:38:20.113"
                },
                {
                    "childMenu": [
                        {
                            "childMenu": null,
                            "id": "7f4acf38-1653-4257-9ae6-140f1b9adc20",
                            "MenuType": "PDA",
                            "MenuLevel": 2,
                            "MenuName": "../static/svg/cx.svg",
                            "MenuFID": "1d94ac78-7036-4f01-95cb-25964f2bb25e",
                            "icon": "",
                            "title": "物料拆箱",
                            "component": "",
                            "path": "materialUnbox",
                            "sonNum": null,
                            "redirect": "/pages/material/unboxing",
                            "sortId": 1,
                            "IsDelete": false,
                            "CreateBy": "CamstarAdmin",
                            "CreateDate": "2024-07-29T09:59:23.027",
                            "UpdateBy": "CamstarAdmin",
                            "UpdateDate": "2024-08-02T19:09:29.64"
                        },
                        {
                            "childMenu": null,
                            "id": "db85a13e-9609-4290-9678-2dd274d7b219",
                            "MenuType": "PDA",
                            "MenuLevel": 2,
                            "MenuName": "../static/svg/wlsl.svg",
                            "MenuFID": "1d94ac78-7036-4f01-95cb-25964f2bb25e",
                            "icon": "",
                            "title": "物料上料",
                            "component": "",
                            "path": "materialFeeding",
                            "sonNum": null,
                            "redirect": "/pages/material/Feeding/index",
                            "sortId": 3,
                            "IsDelete": false,
                            "CreateBy": "CamstarAdmin",
                            "CreateDate": "2024-08-30T17:13:01.19",
                            "UpdateBy": "CamstarAdmin",
                            "UpdateDate": "2024-08-30T17:22:38.907"
                        }
                    ],
                    "id": "1d94ac78-7036-4f01-95cb-25964f2bb25e",
                    "MenuType": "PDA",
                    "MenuLevel": 1,
                    "MenuName": "",
                    "MenuFID": "32138c7a-8a65-4603-8933-5765f5d31543",
                    "icon": "",
                    "title": "物料管理",
                    "component": "",
                    "path": "物料",
                    "sonNum": null,
                    "redirect": "",
                    "sortId": 3,
                    "IsDelete": false,
                    "CreateBy": "CamstarAdmin",
                    "CreateDate": "2024-07-29T09:37:47",
                    "UpdateBy": "CamstarAdmin",
                    "UpdateDate": "2024-08-15T15:13:34.753"
                },
                {
                    "childMenu": [
                        {
                            "childMenu": null,
                            "id": "87327a84-feb8-40a4-ae04-36eb271a4ef1",
                            "MenuType": "PDA",
                            "MenuLevel": 1,
                            "MenuName": "../static/svg/zjsj.svg",
                            "MenuFID": "0c7883d7-2aa4-429a-84f8-49cdca608b1b",
                            "icon": "",
                            "title": "工治具入库",
                            "component": "",
                            "path": "fixtureShelves",
                            "sonNum": null,
                            "redirect": "/pages/permanage/fixtureShelves",
                            "sortId": 7,
                            "IsDelete": false,
                            "CreateBy": "yixi",
                            "CreateDate": "2024-08-27T17:13:05.5",
                            "UpdateBy": "CamstarAdmin",
                            "UpdateDate": "2024-09-04T11:42:41.47"
                        },
                        {
                            "childMenu": null,
                            "id": "bbde96ad-5a6e-4673-958f-1fd2ccaa6879",
                            "MenuType": "PDA",
                            "MenuLevel": 1,
                            "MenuName": "../static/svg/zjfl.svg",
                            "MenuFID": "0c7883d7-2aa4-429a-84f8-49cdca608b1b",
                            "icon": "",
                            "title": "工治具出库",
                            "component": "",
                            "path": "fixtureIssue",
                            "sonNum": null,
                            "redirect": "/pages/permanage/fixtureIssue/index",
                            "sortId": 8,
                            "IsDelete": false,
                            "CreateBy": "yixi",
                            "CreateDate": "2024-08-27T17:13:39.86",
                            "UpdateBy": "CamstarAdmin",
                            "UpdateDate": "2024-09-04T11:42:58.853"
                        },
                        {
                            "childMenu": null,
                            "id": "808d9289-46f9-464a-bc81-ec6eecd8f8c3",
                            "MenuType": "PDA",
                            "MenuLevel": 1,
                            "MenuName": "../static/svg/zjsl.svg",
                            "MenuFID": "0c7883d7-2aa4-429a-84f8-49cdca608b1b",
                            "icon": "",
                            "title": "工治具上线",
                            "component": "",
                            "path": "fixtureIssue",
                            "sonNum": null,
                            "redirect": "/pages/permanage/fixtureOnline/index",
                            "sortId": 9,
                            "IsDelete": false,
                            "CreateBy": "yixi",
                            "CreateDate": "2024-08-29T16:45:09.34",
                            "UpdateBy": "CamstarAdmin",
                            "UpdateDate": "2024-09-04T11:43:05.927"
                        },
                        {
                            "childMenu": null,
                            "id": "fe0a7528-4c78-4205-8764-5282128ac8b3",
                            "MenuType": "PDA",
                            "MenuLevel": 1,
                            "MenuName": "../static/svg/zjxx.svg",
                            "MenuFID": "0c7883d7-2aa4-429a-84f8-49cdca608b1b",
                            "icon": "",
                            "title": "工治具下线",
                            "component": "",
                            "path": "offline",
                            "sonNum": null,
                            "redirect": "/pages/fixture/offline/index",
                            "sortId": 10,
                            "IsDelete": false,
                            "CreateBy": "yixi",
                            "CreateDate": "2024-09-04T14:46:02.313",
                            "UpdateBy": "CamstarAdmin",
                            "UpdateDate": "2024-09-04T14:47:34.487"
                        }
                    ],
                    "id": "0c7883d7-2aa4-429a-84f8-49cdca608b1b",
                    "MenuType": "PDA",
                    "MenuLevel": 1,
                    "MenuName": "",
                    "MenuFID": "32138c7a-8a65-4603-8933-5765f5d31543",
                    "icon": "",
                    "title": "治具房",
                    "component": "",
                    "path": "治具房",
                    "sonNum": 1,
                    "redirect": "",
                    "sortId": 4,
                    "IsDelete": false,
                    "CreateBy": "CamstarAdmin",
                    "CreateDate": "2024-09-04T11:21:36.037",
                    "UpdateBy": "CamstarAdmin",
                    "UpdateDate": "2024-08-15T15:13:34.753"
                }
            ],
            "id": "32138c7a-8a65-4603-8933-5765f5d31543",
            "MenuType": "PDA",
            "MenuLevel": 0,
            "MenuName": "PDA",
            "MenuFID": "",
            "icon": "",
            "title": "PDA",
            "component": "",
            "path": "",
            "sonNum": 2,
            "redirect": null,
            "sortId": 2,
            "IsDelete": false,
            "CreateBy": null,
            "CreateDate": null,
            "UpdateBy": null,
            "UpdateDate": null
        },
        {
            "childMenu": [
                {
                    "childMenu": [
                        {
                            "childMenu": null,
                            "id": "d05430ab-0c5b-42f6-8208-5386145b7b01",
                            "MenuType": "OPUI",
                            "MenuLevel": 2,
                            "MenuName": "BICV-ZZYB-SC-SLJ-001",
                            "MenuFID": "ec171a96-e1b1-4a71-8d10-b9ca4034f8a8",
                            "icon": "",
                            "title": "自动烧录机01",
                            "component": "smtWork/Burn",
                            "path": "Burn",
                            "sonNum": null,
                            "redirect": "",
                            "sortId": 1,
                            "IsDelete": false,
                            "CreateBy": "CamstarAdmin",
                            "CreateDate": "2024-08-02T15:57:11.437",
                            "UpdateBy": "CamstarAdmin",
                            "UpdateDate": "2024-08-18T18:17:11.59"
                        },
                        {
                            "childMenu": null,
                            "id": "d48a4656-def0-4e87-8660-f9a52ecb4ce2",
                            "MenuType": "OPUI",
                            "MenuLevel": 1,
                            "MenuName": "BICV-ZZYB-SB-LDJ-002",
                            "MenuFID": "ec171a96-e1b1-4a71-8d10-b9ca4034f8a8",
                            "icon": "",
                            "title": "镭雕机01",
                            "component": "smtWork/radiumCarving",
                            "path": "radiumCarving",
                            "sonNum": null,
                            "redirect": "",
                            "sortId": 2,
                            "IsDelete": false,
                            "CreateBy": "CamstarAdmin",
                            "CreateDate": "2024-08-01T09:13:01.603",
                            "UpdateBy": "CamstarAdmin",
                            "UpdateDate": "2024-08-18T18:17:32.657"
                        },
                        {
                            "childMenu": null,
                            "id": "8be0282c-af4c-4433-8562-e2d37f7e60d0",
                            "MenuType": "OPUI",
                            "MenuLevel": 1,
                            "MenuName": "BICV-SMT-0001",
                            "MenuFID": "ec171a96-e1b1-4a71-8d10-b9ca4034f8a8",
                            "icon": "",
                            "title": "半成品装箱01",
                            "component": "smtWork/semiFinished",
                            "path": "semiFinished",
                            "sonNum": null,
                            "redirect": "",
                            "sortId": 3,
                            "IsDelete": false,
                            "CreateBy": "CamstarAdmin",
                            "CreateDate": "2024-08-16T09:15:20.813",
                            "UpdateBy": "CamstarAdmin",
                            "UpdateDate": "2024-08-20T10:52:43.593"
                        },
                        {
                            "childMenu": null,
                            "id": "de5a22ab-0a9d-487b-a867-64d3d592bca5",
                            "MenuType": "OPUI",
                            "MenuLevel": 1,
                            "MenuName": "BICV-SMT-0002",
                            "MenuFID": "ec171a96-e1b1-4a71-8d10-b9ca4034f8a8",
                            "icon": "",
                            "title": "半成品装箱02",
                            "component": "smtWork/semiFinished",
                            "path": "semiFinished",
                            "sonNum": 0,
                            "redirect": "",
                            "sortId": 4,
                            "IsDelete": false,
                            "CreateBy": "CamstarAdmin",
                            "CreateDate": "2024-08-22T11:09:31.963",
                            "UpdateBy": "CamstarAdmin",
                            "UpdateDate": "2024-08-20T10:52:43.593"
                        }
                    ],
                    "id": "ec171a96-e1b1-4a71-8d10-b9ca4034f8a8",
                    "MenuType": "OPUI",
                    "MenuLevel": 1,
                    "MenuName": "SmtWorkshop",
                    "MenuFID": "8358d9c8-f8a3-443c-ba92-0b9d4b4e0727",
                    "icon": "",
                    "title": "SMT车间",
                    "component": "Layout",
                    "path": "/smtWorkshop",
                    "sonNum": null,
                    "redirect": "",
                    "sortId": 2,
                    "IsDelete": false,
                    "CreateBy": "CamstarAdmin",
                    "CreateDate": "2024-08-01T20:14:19.59",
                    "UpdateBy": "CamstarAdmin",
                    "UpdateDate": "2024-08-05T13:23:16.713"
                },
                {
                    "childMenu": [
                        {
                            "childMenu": null,
                            "id": "c301c5a3-2357-4689-a8e8-291ace94a497",
                            "MenuType": "OPUI",
                            "MenuLevel": 2,
                            "MenuName": "BICV-ZZEB-SC-XZH-063",
                            "MenuFID": "7b8f99a7-56a0-433b-a3e4-3c053ec71bee",
                            "icon": "",
                            "title": "离线分板机01",
                            "component": "dipWork/PCBSplit",
                            "path": "pcbSplit",
                            "sonNum": null,
                            "redirect": "",
                            "sortId": 1,
                            "IsDelete": false,
                            "CreateBy": "CamstarAdmin",
                            "CreateDate": "2024-08-05T20:07:16.097",
                            "UpdateBy": "CamstarAdmin",
                            "UpdateDate": "2024-08-18T18:06:14.693"
                        },
                        {
                            "childMenu": null,
                            "id": "f639a791-614b-461a-aa14-729c6a131e01",
                            "MenuType": "OPUI",
                            "MenuLevel": 2,
                            "MenuName": "BICV-DIP-0001",
                            "MenuFID": "7b8f99a7-56a0-433b-a3e4-3c053ec71bee",
                            "icon": "",
                            "title": "插件01",
                            "component": "dipWork/PCBPlugIn",
                            "path": "pcbPlugIn",
                            "sonNum": null,
                            "redirect": "",
                            "sortId": 101,
                            "IsDelete": false,
                            "CreateBy": "CamstarAdmin",
                            "CreateDate": "2024-08-07T20:11:04.753",
                            "UpdateBy": "CamstarAdmin",
                            "UpdateDate": "2024-08-21T10:56:27.413"
                        },
                        {
                            "childMenu": null,
                            "id": "1abb3650-dbbb-469e-90a4-f7ecede6a1f6",
                            "MenuType": "OPUI",
                            "MenuLevel": 2,
                            "MenuName": "BICV-DIP-0003",
                            "MenuFID": "7b8f99a7-56a0-433b-a3e4-3c053ec71bee",
                            "icon": "",
                            "title": "目检01",
                            "component": "dipWork/PCBPlugIn",
                            "path": "pcbPlugIn",
                            "sonNum": null,
                            "redirect": "",
                            "sortId": 102,
                            "IsDelete": false,
                            "CreateBy": "CamstarAdmin",
                            "CreateDate": "2024-08-21T10:56:50.073",
                            "UpdateBy": "CamstarAdmin",
                            "UpdateDate": "2024-08-21T13:35:38.137"
                        },
                        {
                            "childMenu": null,
                            "id": "fa1de00c-446b-483d-8056-15564bed0e71",
                            "MenuType": "OPUI",
                            "MenuLevel": 2,
                            "MenuName": "BICV-DIP-0004",
                            "MenuFID": "7b8f99a7-56a0-433b-a3e4-3c053ec71bee",
                            "icon": "",
                            "title": "人工目检02",
                            "component": "dipWork/PCBPlugIn",
                            "path": "pcbPlugIn",
                            "sonNum": 0,
                            "redirect": "",
                            "sortId": 103,
                            "IsDelete": false,
                            "CreateBy": "CamstarAdmin",
                            "CreateDate": "2024-08-21T10:57:08.75",
                            "UpdateBy": "CamstarAdmin",
                            "UpdateDate": "2024-08-21T10:56:55.477"
                        },
                        {
                            "childMenu": null,
                            "id": "a39021c3-a90e-48af-893d-d0199e957053",
                            "MenuType": "OPUI",
                            "MenuLevel": 2,
                            "MenuName": "BICV-DIP-0002",
                            "MenuFID": "7b8f99a7-56a0-433b-a3e4-3c053ec71bee",
                            "icon": "",
                            "title": "插件02",
                            "component": "dipWork/PCBPlugIn",
                            "path": "pcbPlugIn",
                            "sonNum": null,
                            "redirect": "",
                            "sortId": 201,
                            "IsDelete": false,
                            "CreateBy": "CamstarAdmin",
                            "CreateDate": "2024-08-21T10:55:31.69",
                            "UpdateBy": "CamstarAdmin",
                            "UpdateDate": "2024-08-21T10:56:15.367"
                        },
                        {
                            "childMenu": null,
                            "id": "e96d5e28-c983-438c-bdc2-d0ce84265797",
                            "MenuType": "OPUI",
                            "MenuLevel": 2,
                            "MenuName": "BICV-ZZEB-SC-XZH-062",
                            "MenuFID": "7b8f99a7-56a0-433b-a3e4-3c053ec71bee",
                            "icon": "",
                            "title": "选择焊01",
                            "component": "dipWork/ChooseWelding",
                            "path": "pcbSplit",
                            "sonNum": null,
                            "redirect": "",
                            "sortId": 202,
                            "IsDelete": false,
                            "CreateBy": "CamstarAdmin",
                            "CreateDate": "2024-08-15T10:00:03.633",
                            "UpdateBy": "CamstarAdmin",
                            "UpdateDate": "2024-08-21T10:56:21.55"
                        }
                    ],
                    "id": "7b8f99a7-56a0-433b-a3e4-3c053ec71bee",
                    "MenuType": "OPUI",
                    "MenuLevel": 1,
                    "MenuName": "",
                    "MenuFID": "8358d9c8-f8a3-443c-ba92-0b9d4b4e0727",
                    "icon": "",
                    "title": "DIP车间",
                    "component": "Layout",
                    "path": "/dipWorkshop",
                    "sonNum": null,
                    "redirect": "",
                    "sortId": 3,
                    "IsDelete": false,
                    "CreateBy": "CamstarAdmin",
                    "CreateDate": "2024-08-05T20:02:59.603",
                    "UpdateBy": "CamstarAdmin",
                    "UpdateDate": "2024-08-30T17:04:11.823"
                },
                {
                    "childMenu": [
                        {
                            "childMenu": null,
                            "id": "714eda6e-f6a1-4453-99bc-7693c586c5b3",
                            "MenuType": "OPUI",
                            "MenuLevel": 1,
                            "MenuName": "BICV-SCN-0002",
                            "MenuFID": "10ded34b-4bff-46d5-9365-1c8f2b6eb338",
                            "icon": "",
                            "title": "来料外观检验01",
                            "component": "screenWork/appearance",
                            "path": "appearance",
                            "sonNum": null,
                            "redirect": "",
                            "sortId": 2,
                            "IsDelete": false,
                            "CreateBy": "CamstarAdmin",
                            "CreateDate": "2024-08-01T20:23:09.68",
                            "UpdateBy": "CamstarAdmin",
                            "UpdateDate": "2024-08-26T21:23:53.003"
                        },
                        {
                            "childMenu": null,
                            "id": "4e1beabc-73fa-4496-ab7d-f42246569012",
                            "MenuType": "OPUI",
                            "MenuLevel": 2,
                            "MenuName": "BICV-SCN-0003",
                            "MenuFID": "10ded34b-4bff-46d5-9365-1c8f2b6eb338",
                            "icon": "",
                            "title": "来料功能检验01",
                            "component": "screenWork/function",
                            "path": "function",
                            "sonNum": null,
                            "redirect": "",
                            "sortId": 3,
                            "IsDelete": false,
                            "CreateBy": "CamstarAdmin",
                            "CreateDate": "2024-08-07T16:55:56.457",
                            "UpdateBy": "CamstarAdmin",
                            "UpdateDate": "2024-08-26T21:23:58.957"
                        },
                        {
                            "childMenu": null,
                            "id": "fee0942e-9d0e-49c6-b95a-cca63af11461",
                            "MenuType": "OPUI",
                            "MenuLevel": 2,
                            "MenuName": "BICV-SCN-0004",
                            "MenuFID": "10ded34b-4bff-46d5-9365-1c8f2b6eb338",
                            "icon": "",
                            "title": "不良复判01",
                            "component": "screenWork/disposalProduct",
                            "path": "disposalProduct",
                            "sonNum": null,
                            "redirect": "",
                            "sortId": 9,
                            "IsDelete": false,
                            "CreateBy": "CamstarAdmin",
                            "CreateDate": "2024-08-20T20:48:50.337",
                            "UpdateBy": "CamstarAdmin",
                            "UpdateDate": "2024-08-26T21:25:56.803"
                        },
                        {
                            "childMenu": null,
                            "id": "fd763405-e750-4771-8eb3-8d6718691c02",
                            "MenuType": "OPUI",
                            "MenuLevel": 2,
                            "MenuName": "BICV-SCN-0005",
                            "MenuFID": "10ded34b-4bff-46d5-9365-1c8f2b6eb338",
                            "icon": "",
                            "title": "不良拆解01",
                            "component": "screenWork/dismantleProduct",
                            "path": "dismantleProduct",
                            "sonNum": null,
                            "redirect": "",
                            "sortId": 10,
                            "IsDelete": false,
                            "CreateBy": "CamstarAdmin",
                            "CreateDate": "2024-08-20T20:49:21.737",
                            "UpdateBy": "CamstarAdmin",
                            "UpdateDate": "2024-08-26T21:25:44.833"
                        },
                        {
                            "childMenu": null,
                            "id": "49277748-3c0c-4e4b-9124-5cc746ff57cc",
                            "MenuType": "OPUI",
                            "MenuLevel": 2,
                            "MenuName": "BICV10403764",
                            "MenuFID": "10ded34b-4bff-46d5-9365-1c8f2b6eb338",
                            "icon": "",
                            "title": "全自动贴合机01",
                            "component": "screenWork/jointdown",
                            "path": "jointdown",
                            "sonNum": null,
                            "redirect": "",
                            "sortId": 21,
                            "IsDelete": false,
                            "CreateBy": "CamstarAdmin",
                            "CreateDate": "2024-08-13T19:58:19.02",
                            "UpdateBy": "CamstarAdmin",
                            "UpdateDate": "2024-08-26T21:24:53.6"
                        },
                        {
                            "childMenu": null,
                            "id": "68897e9b-5058-4b97-be54-2326865256e1",
                            "MenuType": "OPUI",
                            "MenuLevel": 2,
                            "MenuName": "BICV10403756",
                            "MenuFID": "10ded34b-4bff-46d5-9365-1c8f2b6eb338",
                            "icon": "",
                            "title": "脱泡机01",
                            "component": "screenWork/jointdeaeration",
                            "path": "jointdeaeration",
                            "sonNum": null,
                            "redirect": "",
                            "sortId": 22,
                            "IsDelete": false,
                            "CreateBy": "CamstarAdmin",
                            "CreateDate": "2024-08-13T20:05:26.627",
                            "UpdateBy": "CamstarAdmin",
                            "UpdateDate": "2024-08-26T21:25:04.077"
                        },
                        {
                            "childMenu": null,
                            "id": "7d43b283-4eaa-4d84-be48-9da10a77df19",
                            "MenuType": "OPUI",
                            "MenuLevel": 2,
                            "MenuName": "BICV10404495",
                            "MenuFID": "10ded34b-4bff-46d5-9365-1c8f2b6eb338",
                            "icon": "",
                            "title": "高温老化01",
                            "component": "screenWork/function",
                            "path": "function",
                            "sonNum": null,
                            "redirect": "SCN-Aging-01",
                            "sortId": 23,
                            "IsDelete": false,
                            "CreateBy": "CamstarAdmin",
                            "CreateDate": "2024-08-14T15:41:13.167",
                            "UpdateBy": "CamstarAdmin",
                            "UpdateDate": "2024-09-05T16:59:58.933"
                        },
                        {
                            "childMenu": null,
                            "id": "9b0ed7c6-50ec-4bf0-8b05-f85917dbb2b6",
                            "MenuType": "OPUI",
                            "MenuLevel": 2,
                            "MenuName": "BICV10403759",
                            "MenuFID": "10ded34b-4bff-46d5-9365-1c8f2b6eb338",
                            "icon": "",
                            "title": "UV固化01",
                            "component": "screenWork/UASolidification",
                            "path": "UASolidification",
                            "sonNum": null,
                            "redirect": "",
                            "sortId": 24,
                            "IsDelete": false,
                            "CreateBy": "CamstarAdmin",
                            "CreateDate": "2024-08-14T15:43:11.94",
                            "UpdateBy": "CamstarAdmin",
                            "UpdateDate": "2024-08-26T21:25:27.917"
                        }
                    ],
                    "id": "10ded34b-4bff-46d5-9365-1c8f2b6eb338",
                    "MenuType": "OPUI",
                    "MenuLevel": 1,
                    "MenuName": "ScreenWork",
                    "MenuFID": "8358d9c8-f8a3-443c-ba92-0b9d4b4e0727",
                    "icon": "",
                    "title": "屏车间",
                    "component": "Layout",
                    "path": "/screenWork",
                    "sonNum": null,
                    "redirect": "",
                    "sortId": 4,
                    "IsDelete": false,
                    "CreateBy": "CamstarAdmin",
                    "CreateDate": "2024-08-01T09:09:05.483",
                    "UpdateBy": "CamstarAdmin",
                    "UpdateDate": "2024-08-05T20:03:30.057"
                }
            ],
            "id": "8358d9c8-f8a3-443c-ba92-0b9d4b4e0727",
            "MenuType": null,
            "MenuLevel": 0,
            "MenuName": "OPUI",
            "MenuFID": "",
            "icon": "",
            "title": "OPUI",
            "component": "",
            "path": "",
            "sonNum": null,
            "redirect": "",
            "sortId": 3,
            "IsDelete": false,
            "CreateBy": "CamstarAdmin",
            "CreateDate": "2024-07-26T16:56:49.713",
            "UpdateBy": "CamstarAdmin",
            "UpdateDate": "2024-07-26T16:58:36.457"
        }
    ],
    "content2": null
}